invenio_preservation_sync/__init__.py
invenio_preservation_sync/config.py
invenio_preservation_sync/errors.py
invenio_preservation_sync/ext.py
invenio_preservation_sync/models.py
invenio_preservation_sync/proxies.py
invenio_preservation_sync/receivers.py
invenio_preservation_sync/utils.py
invenio_preservation_sync/alembic/2e6fbe6998cc_create_preservation_info_tables.py
invenio_preservation_sync/alembic/7983d81b23cb_create_preservation_info_branch.py
invenio_preservation_sync/resources/__init__.py
invenio_preservation_sync/resources/config.py
invenio_preservation_sync/resources/resource.py
invenio_preservation_sync/services/__init__.py
invenio_preservation_sync/services/config.py
invenio_preservation_sync/services/permissions.py
invenio_preservation_sync/services/results.py
invenio_preservation_sync/services/schemas.py
invenio_preservation_sync/services/service.py
invenio_preservation_sync/templates/semantic-ui/invenio_preservation_sync/preservation_link.html
tests/__init__.py
tests/conftest.py
tests/test_alembic.py
tests/test_invenio_preservation_sync.py
tests/test_receivers.py
tests/test_resource.py
invenio_preservation_sync-0.2.0.dist-info/AUTHORS.rst
invenio_preservation_sync-0.2.0.dist-info/LICENSE
invenio_preservation_sync-0.2.0.dist-info/METADATA
invenio_preservation_sync-0.2.0.dist-info/WHEEL
invenio_preservation_sync-0.2.0.dist-info/entry_points.txt
invenio_preservation_sync-0.2.0.dist-info/top_level.txt
invenio_preservation_sync-0.2.0.dist-info/RECORD
