Metadata-Version: 2.2
Name: invenio-preservation-sync
Version: 0.2.0
Summary: Invenio module that adds preservation sync integration to the platform.
Home-page: https://github.com/inveniosoftware/invenio-preservation-sync
Author: CERN
Author-email: info@inveniosoftware.org
License: MIT
Keywords: invenio preservation
Platform: any
Classifier: Development Status :: 1 - Planning
Requires-Python: >=3.7
License-File: LICENSE
License-File: AUTHORS.rst
Requires-Dist: invenio-base<3.0.0,>=2.0.0
Requires-Dist: invenio-db<3.0.0,>=2.0.0
Requires-Dist: invenio-webhooks<2.0.0,>=1.0.0
Requires-Dist: invenio-records-permissions<2.0.0,>=1.0.0
Requires-Dist: invenio-pidstore<3.0.0,>=2.0.0
Requires-Dist: invenio-i18n<4.0.0,>=3.0.0
Requires-Dist: flask-resources<2.0.0,>=1.0.0
Requires-Dist: marshmallow-utils<1.0.0,>=0.7.1
Provides-Extra: tests
Requires-Dist: invenio-app>=1.3.4; extra == "tests"
Requires-Dist: pytest-invenio>=3.0.0; extra == "tests"
Requires-Dist: pytest-black-ng>=0.4.0; extra == "tests"
Requires-Dist: sphinx>=4.5.0; extra == "tests"
Requires-Dist: invenio-db[mysql,postgresql]>=2.0.0; extra == "tests"
Provides-Extra: elasticsearch7
Requires-Dist: invenio-search[elasticsearch7]<4.0.0,>=3.0.0; extra == "elasticsearch7"
Provides-Extra: opensearch1
Requires-Dist: invenio-search[opensearch1]<4.0.0,>=3.0.0; extra == "opensearch1"
Provides-Extra: opensearch2
Requires-Dist: invenio-search[opensearch2]<4.0.0,>=3.0.0; extra == "opensearch2"
